goat_wallets/evm/__init__.py
goat_wallets/evm/evm_smart_wallet_client.py
goat_wallets/evm/evm_wallet_client.py
goat_wallets/evm/send_eth.py
goat_wallets/evm/types.py
goat_sdk_wallet_evm-0.1.2.dist-info/METADATA
goat_sdk_wallet_evm-0.1.2.dist-info/WHEEL
goat_sdk_wallet_evm-0.1.2.dist-info/RECORD
